LICENSE
MANIFEST.in
README.rst
setup.py
geokey_sapelli/__init__.py
geokey_sapelli/manager.py
geokey_sapelli/models.py
geokey_sapelli/serializers.py
geokey_sapelli/urls.py
geokey_sapelli/views.py
geokey_sapelli.egg-info/PKG-INFO
geokey_sapelli.egg-info/SOURCES.txt
geokey_sapelli.egg-info/dependency_links.txt
geokey_sapelli.egg-info/requires.txt
geokey_sapelli.egg-info/top_level.txt
geokey_sapelli/helper/__init__.py
geokey_sapelli/helper/csv_helpers.py
geokey_sapelli/helper/install_checks.py
geokey_sapelli/helper/project_mapper.py
geokey_sapelli/helper/sapelli_exceptions.py
geokey_sapelli/helper/sapelli_loader.py
geokey_sapelli/migrations/0001_initial.py
geokey_sapelli/migrations/0002_sapellichoiceroot_sapelli_id.py
geokey_sapelli/migrations/0003_auto_20150512_1533.py
geokey_sapelli/migrations/0004_locationfield.py
geokey_sapelli/migrations/0005_sapellifield_truefalse.py
geokey_sapelli/migrations/0006_sapelliproject_sapelli_fingerprint.py
geokey_sapelli/migrations/0007_deleted_projects.py
geokey_sapelli/migrations/0008_additional_project_and_form_fields.py
geokey_sapelli/migrations/0009_rename_project_to_geokey_project.py
geokey_sapelli/migrations/0010_choice_root_path_image.py
geokey_sapelli/migrations/0011_dir_path_sap_path.py
geokey_sapelli/migrations/0012_remove_sapelliitem_image.py
geokey_sapelli/migrations/0013_sapdownloadqrlink.py
geokey_sapelli/migrations/0014_fix_everyone_contributes.py
geokey_sapelli/migrations/0015_remove_automatic_descriptions.py
geokey_sapelli/migrations/0016_fix_old_sapelli_projects.py
geokey_sapelli/migrations/0017_fix_descriptions.py
geokey_sapelli/migrations/0018_sapellilogfile.py
geokey_sapelli/migrations/__init__.py
geokey_sapelli/static/lib/js-cookie/js.cookie.min.js
geokey_sapelli/templates/sapelli/index.html
geokey_sapelli/templates/sapelli/logs.html
geokey_sapelli/templates/sapelli/upload_data_csv.html
geokey_sapelli/templates/sapelli/upload_sapelli_project.html
geokey_sapelli/templates/sapelli/snippets/header.html
geokey_sapelli/templates/sapelli/snippets/messages.html
geokey_sapelli/templates/sapelli/snippets/navigation.html
geokey_sapelli/templatetags/__init__.py
geokey_sapelli/templatetags/sapelli_tags.py