Metadata-Version: 1.1
Name: geokey-sapelli
Version: 2.0.1
Summary: Read Sapelli project and load data from CSVs to GeoKey
Home-page: https://github.com/ExCiteS/geokey-sapelli
Author: ExCiteS
Author-email: excites@ucl.ac.uk
License: UNKNOWN
Download-URL: https://github.com/ExCiteS/geokey-sapelli/tarball/2.0.1
Platform: UNKNOWN
